dailytools/__exceptions.py
dailytools/__init__.py
dailytools/logger.py
dailytools/utils.py
dailytools/audio/__init__.py
dailytools/audio/audio_db.py
dailytools/audio/headers.py
dailytools/audio/tts_engine.py
dailytools/audio/utils.py
dailytools/encrypt/__sm4.py
dailywheels-1.0.1.dist-info/LICENSE.TXT
dailywheels-1.0.1.dist-info/METADATA
dailywheels-1.0.1.dist-info/WHEEL
dailywheels-1.0.1.dist-info/top_level.txt
dailywheels-1.0.1.dist-info/zip-safe
dailywheels-1.0.1.dist-info/RECORD
